README.rst
setup.cfg
setup.py
pickleback/__init__.py
pickleback/__main__.py
pickleback/backend_pkl.py
pickleback/saveas.py
pickleback.egg-info/PKG-INFO
pickleback.egg-info/SOURCES.txt
pickleback.egg-info/dependency_links.txt
pickleback.egg-info/top_level.txt