Metadata-Version: 1.1
Name: pickleback
Version: 0.1a2
Summary: Matplotlib backend defining export to pickle (extension .pkl or .pickle).
Home-page: https://pickleback.readthedocs.io
Author: Joel Nothman
Author-email: joel.nothman@gmail.com
License: BSD 3-Clause License
Platform: UNKNOWN
Classifier: Programming Language :: Python :: 2
Classifier: Programming Language :: Python :: 2.7
Classifier: Programming Language :: Python :: 3
Classifier: Programming Language :: Python :: 3.5
Classifier: Programming Language :: Python :: 3.6
